securesystemslib/__init__.py
securesystemslib/ecdsa_keys.py
securesystemslib/ed25519_keys.py
securesystemslib/exceptions.py
securesystemslib/formats.py
securesystemslib/hash.py
securesystemslib/interface.py
securesystemslib/keys.py
securesystemslib/pyca_crypto_keys.py
securesystemslib/schema.py
securesystemslib/settings.py
securesystemslib/unittest_toolbox.py
securesystemslib/util.py
securesystemslib/_vendor/__init__.py
securesystemslib/_vendor/ssl_match_hostname.py
securesystemslib/_vendor/ed25519/__init__.py
securesystemslib/_vendor/ed25519/ed25519.py
securesystemslib/_vendor/ed25519/science.py
securesystemslib/_vendor/ed25519/test_ed25519.py
oll_securesystemslib-0.11.3.dev7.dist-info/LICENSE
oll_securesystemslib-0.11.3.dev7.dist-info/METADATA
oll_securesystemslib-0.11.3.dev7.dist-info/WHEEL
oll_securesystemslib-0.11.3.dev7.dist-info/top_level.txt
oll_securesystemslib-0.11.3.dev7.dist-info/RECORD
