Metadata-Version: 2.1
Name: oll-securesystemslib
Version: 0.11.3.dev7
Summary: Open Law Library's fork of securesystemslib
Home-page: https://github.com/secure-systems-lab/securesystemslib
Author: https://www.updateframework.com
Author-email: theupdateframework@googlegroups.com
License: UNKNOWN
Keywords: cryptography,keys,signatures,rsa,ed25519,ecdsa
Platform: UNKNOWN
Classifier: Development Status :: 4 - Beta
Classifier: Intended Audience :: Developers
Classifier: License :: OSI Approved :: MIT License
Classifier: Natural Language :: English
Classifier: Operating System :: POSIX
Classifier: Operating System :: POSIX :: Linux
Classifier: Operating System :: MacOS :: MacOS X
Classifier: Operating System :: Microsoft :: Windows
Classifier: Programming Language :: Python
Classifier: Programming Language :: Python :: 2
Classifier: Programming Language :: Python :: 2.7
Classifier: Programming Language :: Python :: 3
Classifier: Programming Language :: Python :: 3.4
Classifier: Programming Language :: Python :: 3.5
Classifier: Programming Language :: Python :: 3.6
Classifier: Programming Language :: Python :: Implementation :: CPython
Classifier: Topic :: Security
Classifier: Topic :: Software Development
Requires-Dist: six (>=1.11.0)
Provides-Extra: crypto
Requires-Dist: cryptography (>=2.2.2) ; extra == 'crypto'
Requires-Dist: colorama (>=0.3.9) ; extra == 'crypto'
Provides-Extra: pynacl
Requires-Dist: pynacl (>1.2.0) ; extra == 'pynacl'
